Weverse/__init__.py
Weverse/error.py
Weverse/objects.py
Weverse/weverseasync.py
Weverse/weverseclient.py
Weverse/weversesync.py
Weverse/models/__init__.py
Weverse/models/announcement.py
Weverse/models/artist.py
Weverse/models/comment.py
Weverse/models/community.py
Weverse/models/media.py
Weverse/models/notification.py
Weverse/models/photo.py
Weverse/models/post.py
Weverse/models/tab.py
Weverse/models/video.py
Weverse-1.1.8.2.dist-info/LICENSE
Weverse-1.1.8.2.dist-info/METADATA
Weverse-1.1.8.2.dist-info/WHEEL
Weverse-1.1.8.2.dist-info/top_level.txt
Weverse-1.1.8.2.dist-info/RECORD
