Metadata-Version: 2.1
Name: Weverse
Version: 1.1.8.2
Summary: Creates internal cache for the communities a user follows on weverse.io
Home-page: https://github.com/MujyKun/Weverse/
Author: MujyKun
Author-email: mujy@irenebot.com
License: MIT License
Classifier: Development Status :: 5 - Production/Stable
Classifier: License :: OSI Approved :: MIT License
Classifier: Programming Language :: Python
Requires-Python: >=3.6
License-File: LICENSE
Requires-Dist: aiohttp (>=3.6.2)
Requires-Dist: requests (>=2.22.0)
Requires-Dist: asyncio (~=3.4.3)
Requires-Dist: setuptools (~=57.0.0)
Requires-Dist: pycryptodome (==3.10.1)
Requires-Dist: aiofiles (~=0.8.0)
